{"commitInfo":{"timestamp":1777466290503,"operation":"CREATE OR REPLACE TABLE AS SELECT","operationParameters":{"isManaged":"true","description":null,"partitionBy":"[]","properties":"{}"},"readVersion":7,"isolationLevel":"Serializable","isBlindAppend":false,"operationMetrics":{"numFiles":"1","numOutputRows":"4728","numOutputBytes":"222207"},"engineInfo":"Apache-Spark/3.4.1 Delta-Lake/2.4.0","txnId":"be3c7185-b995-461e-a02a-e3451f2b985e"}}
{"metaData":{"id":"53e1aaa0-ff9e-4313-8d12-bedc524b23a3","format":{"provider":"parquet","options":{}},"schemaString":"{\"type\":\"struct\",\"fields\":[{\"name\":\"ticker\",\"type\":\"string\",\"nullable\":true,\"metadata\":{}},{\"name\":\"data_referencia\",\"type\":\"date\",\"nullable\":true,\"metadata\":{}},{\"name\":\"preco_abertura\",\"type\":\"double\",\"nullable\":true,\"metadata\":{}},{\"name\":\"preco_maximo\",\"type\":\"double\",\"nullable\":true,\"metadata\":{}},{\"name\":\"preco_minimo\",\"type\":\"double\",\"nullable\":true,\"metadata\":{}},{\"name\":\"preco_fechamento\",\"type\":\"double\",\"nullable\":true,\"metadata\":{}},{\"name\":\"volume\",\"type\":\"double\",\"nullable\":true,\"metadata\":{}},{\"name\":\"variacao_diaria_pct\",\"type\":\"double\",\"nullable\":true,\"metadata\":{}},{\"name\":\"media_movel_7d\",\"type\":\"double\",\"nullable\":true,\"metadata\":{}}]}","partitionColumns":[],"configuration":{},"createdTime":1777466288442}}
{"add":{"path":"part-00000-b1a3c0f2-7c25-42bc-b510-14ce6cabe68f-c000.snappy.parquet","partitionValues":{},"size":222207,"modificationTime":1777466289118,"dataChange":true,"stats":"{\"numRecords\":4728,\"minValues\":{\"ticker\":\"BBDC4\",\"data_referencia\":\"2024-04-29\",\"preco_abertura\":0.0,\"preco_maximo\":0.0,\"preco_minimo\":0.0,\"preco_fechamento\":10.043407440185547,\"volume\":0.0,\"variacao_diaria_pct\":-6.21621780681525,\"media_movel_7d\":10.045907429286412},\"maxValues\":{\"ticker\":\"VALE3\",\"data_referencia\":\"2026-04-28\",\"preco_abertura\":89.8499984741211,\"preco_maximo\":91.62000274658203,\"preco_minimo\":89.08000183105469,\"preco_fechamento\":90.08999633789062,\"volume\":2.202628E8,\"variacao_diaria_pct\":15.644172071584372,\"media_movel_7d\":88.24857221330915},\"nullCount\":{\"ticker\":0,\"data_referencia\":0,\"preco_abertura\":0,\"preco_maximo\":0,\"preco_minimo\":0,\"preco_fechamento\":0,\"volume\":0,\"variacao_diaria_pct\":4,\"media_movel_7d\":0}}"}}
{"remove":{"path":"part-00000-02195ca8-a253-47b6-a6bc-836e641c8238-c000.snappy.parquet","deletionTimestamp":1777466290488,"dataChange":true,"extendedFileMetadata":true,"partitionValues":{},"size":209035}}
